MANIFEST.in
README.MD
README.md
setup.py
SimpleDicomToolkit/DicomDatabaseSQL.py
SimpleDicomToolkit/SQLiteWrapper.py
SimpleDicomToolkit/__init__.py
SimpleDicomToolkit/dicom_parser.py
SimpleDicomToolkit/dicom_reader.py
SimpleDicomToolkit/dicom_tags.py
SimpleDicomToolkit/file_scanner.py
SimpleDicomToolkit/images_on_disk.py
SimpleDicomToolkit/logger.py
SimpleDicomToolkit/progress_bar.py
SimpleDicomToolkit.egg-info/PKG-INFO
SimpleDicomToolkit.egg-info/SOURCES.txt
SimpleDicomToolkit.egg-info/dependency_links.txt
SimpleDicomToolkit.egg-info/not-zip-safe
SimpleDicomToolkit.egg-info/requires.txt
SimpleDicomToolkit.egg-info/top_level.txt