Metadata-Version: 1.1
Name: SimpleDicomToolkit
Version: 1.4
Summary: Dicom Toolkit for reading dicom files to  SimpleITK images
Home-page: https://github.com/heydude1337/SimpleDicomToolkit
Author: HeyDude
Author-email: heydude1337@gmail.com
License: MIT
Keywords: phantom analysis simpleitk medical dicom
Platform: UNKNOWN
Classifier: Development Status :: 3 - Alpha
Classifier: License :: OSI Approved :: MIT License
Classifier: Programming Language :: Python :: 3.6
Classifier: Topic :: Scientific/Engineering :: Medical Science Apps.
Classifier: Intended Audience :: Science/Research
Classifier: Natural Language :: English
